greenplumpython/__init__.py
greenplumpython/db.py
greenplumpython/expr.py
greenplumpython/func.py
greenplumpython/group.py
greenplumpython/op.py
greenplumpython/order.py
greenplumpython/table.py
greenplumpython/type.py
tests/__init__.py
tests/test_binaryExpr.py
tests/test_builtin.py
tests/test_column.py
tests/test_const_table.py
tests/test_db.py
tests/test_func.py
tests/test_group.py
tests/test_join.py
tests/test_op.py
tests/test_order.py
tests/test_type.py
tests/test_unaryExpr.py
tests/test_union.py
greenplum_python_fork-1.0.0b6.dist-info/LICENSE
greenplum_python_fork-1.0.0b6.dist-info/METADATA
greenplum_python_fork-1.0.0b6.dist-info/WHEEL
greenplum_python_fork-1.0.0b6.dist-info/top_level.txt
greenplum_python_fork-1.0.0b6.dist-info/RECORD
